trame/__init__.py
trame/modules/__init__.py
trame/modules/deckgl.py
trame/widgets/__init__.py
trame/widgets/deckgl.py
trame_deckgl/LICENSE
trame_deckgl/__init__.py
trame_deckgl/module/__init__.py
trame_deckgl/module/serve/trame-deckgl.umd.min.js
trame_deckgl/widgets/__init__.py
trame_deckgl/widgets/deckgl.py
trame_deckgl-2.0.3.dist-info/LICENSE
trame_deckgl-2.0.3.dist-info/METADATA
trame_deckgl-2.0.3.dist-info/WHEEL
trame_deckgl-2.0.3.dist-info/top_level.txt
trame_deckgl-2.0.3.dist-info/RECORD
